{
  "navn": "ULTRAFIOLETT DAMESYKKEL",
  "orgNavn": "ANSTENDIG PIGGSVIN BARNEHAGE",
  "innsenderNavn": "Muskuløs Vals",
  "identitetsnummer": "10486535275",
  "orgnrUnderenhet": "810007842",
  "fravaersperioder": [
    { "fom": "2023-08-25", "tom": "2023-08-28" },
    { "fom": "2023-08-29", "tom": "2023-09-11" },
    { "fom": "2023-09-12", "tom": "2023-10-02" }
  ],
  "egenmeldingsperioder": [],
  "bruttoinntekt": 13806.27,
  "tidligereinntekter": [
    { "maaned": "2023-05", "inntekt": 12028.25 },
    { "maaned": "2023-06", "inntekt": 11730.69 },
    { "maaned": "2023-07", "inntekt": 17659.88 }
  ],
  "skjaeringstidspunkt": "2023-08-23",
  "behandlingsperiode": null,

  "forespurtData": {
    "arbeidsgiverperiode": { "paakrevd": true },
    "inntekt": {
      "paakrevd": false,
      "forslag": {
        "type": "ForslagInntektFastsatt",
        "fastsattInntekt": 99999.27
      }
    },
    "refusjon": {
      "paakrevd": true,
      "forslag": { "perioder": [], "opphoersdato": null }
    }
  }
}
